[
  {
    "full_name": "lerrua/remote-jobs-brazil",
    "stargazers_count": 4483,
    "open_issues_count": 9,
    "forks_count": 478
  },
  {
    "full_name": "remoteintech/remote-jobs",
    "stargazers_count": 25006,
    "open_issues_count": 51,
    "forks_count": 2668
  },
  {
    "full_name": "dwyl/learn-json-web-tokens",
    "stargazers_count": 4175,
    "open_issues_count": 22,
    "forks_count": 267
  },
  {
    "full_name": "pomber/code-surfer",
    "stargazers_count": 6195,
    "open_issues_count": 42,
    "forks_count": 182
  },
  {
    "full_name": "tomhicks/themera",
    "stargazers_count": 107,
    "open_issues_count": 4,
    "forks_count": 15
  },
  {
    "full_name": "resendlabs/react-email",
    "stargazers_count": 8248,
    "open_issues_count": 70,
    "forks_count": 335
  },
  {
    "full_name": "fatih-yavuz/links.dev",
    "stargazers_count": 196,
    "open_issues_count": 0,
    "forks_count": 162
  },
  {
    "full_name": "yanirs/established-remote",
    "stargazers_count": 6259,
    "open_issues_count": 0,
    "forks_count": 526
  },
  {
    "full_name": "billyjov/microfrontend-resources",
    "stargazers_count": 613,
    "open_issues_count": 0,
    "forks_count": 70
  },
  {
    "full_name": "JedWatson/react-select",
    "stargazers_count": 26345,
    "open_issues_count": 322,
    "forks_count": 4065
  },
  {
    "full_name": "argyleink/gui-challenges",
    "stargazers_count": 2423,
    "open_issues_count": 42,
    "forks_count": 337
  },
  {
    "full_name": "micromata/awesome-javascript-learning",
    "stargazers_count": 4774,
    "open_issues_count": 0,
    "forks_count": 579
  },
  {
    "full_name": "0xRadi/OWASP-Web-Checklist",
    "stargazers_count": 1274,
    "open_issues_count": 1,
    "forks_count": 288
  },
  {
    "full_name": "kamranahmedse/design-patterns-for-humans",
    "stargazers_count": 41304,
    "open_issues_count": 11,
    "forks_count": 4898
  },
  {
    "full_name": "total-typescript/beginners-typescript-tutorial",
    "stargazers_count": 7502,
    "open_issues_count": 4,
    "forks_count": 999
  },
  {
    "full_name": "ripienaar/free-for-dev",
    "stargazers_count": 71365,
    "open_issues_count": 11,
    "forks_count": 7817
  },
  {
    "full_name": "bespoyasov/frontend-clean-architecture",
    "stargazers_count": 2015,
    "open_issues_count": 1,
    "forks_count": 224
  },
  {
    "full_name": "mtdvio/every-programmer-should-know",
    "stargazers_count": 71934,
    "open_issues_count": 45,
    "forks_count": 6870
  },
  {
    "full_name": "JanVanRyswyck/awesome-talks",
    "stargazers_count": 5844,
    "open_issues_count": 32,
    "forks_count": 417
  },
  {
    "full_name": "AllThingsSmitty/css-protips",
    "stargazers_count": 25552,
    "open_issues_count": 16,
    "forks_count": 2081
  },
  {
    "full_name": "dypsilon/frontend-dev-bookmarks",
    "stargazers_count": 38701,
    "open_issues_count": 117,
    "forks_count": 5112
  },
  {
    "full_name": "mbrlabs/Lorien",
    "stargazers_count": 3998,
    "open_issues_count": 66,
    "forks_count": 164
  },
  {
    "full_name": "siyuan-note/siyuan",
    "stargazers_count": 11073,
    "open_issues_count": 53,
    "forks_count": 837
  },
  {
    "full_name": "viraptor/reverse-interview",
    "stargazers_count": 25628,
    "open_issues_count": 26,
    "forks_count": 1979
  },
  {
    "full_name": "InterviewReady/system-design-resources",
    "stargazers_count": 10362,
    "open_issues_count": 0,
    "forks_count": 1196
  },
  {
    "full_name": "spacedriveapp/spacedrive",
    "stargazers_count": 20897,
    "open_issues_count": 25,
    "forks_count": 725
  },
  {
    "full_name": "triggerdotdev/jsonhero-web",
    "stargazers_count": 7840,
    "open_issues_count": 56,
    "forks_count": 363
  },
  {
    "full_name": "ryanmcdermott/clean-code-javascript",
    "stargazers_count": 83594,
    "open_issues_count": 92,
    "forks_count": 11360
  },
  {
    "full_name": "thedaviddias/Front-End-Performance-Checklist",
    "stargazers_count": 15892,
    "open_issues_count": 20,
    "forks_count": 1163
  },
  {
    "full_name": "devhubapp/devhub",
    "stargazers_count": 9054,
    "open_issues_count": 45,
    "forks_count": 796
  }
]